swavepy/FresnelZone.py
swavepy/WaveProp.py
swavepy/WavePyClasses.py
swavepy/__init__.py
swavepy/utility_functions.py
swavepy/wavefield_animated.py
swavepy/wavefield_plotting_using_classes.py
swavepy-0.0.2.dist-info/licenses/LICENSE
swavepy-0.0.2.dist-info/METADATA
swavepy-0.0.2.dist-info/WHEEL
swavepy-0.0.2.dist-info/top_level.txt
swavepy-0.0.2.dist-info/RECORD
