Metadata-Version: 2.4
Name: swavepy
Version: 0.0.2
Summary: seismic wave modelling
Author: Nienke Blom, Will Pizii
License:                     GNU GENERAL PUBLIC LICENSE
License-File: LICENSE
Requires-Dist: ipympl
Requires-Dist: matplotlib
Requires-Dist: numpy
Requires-Dist: numba
Dynamic: license-file
